annotation_utils/__init__.py
annotation_utils/base/__init__.py
annotation_utils/base/basic.py
annotation_utils/base/structs.py
annotation_utils/coco/__init__.py
annotation_utils/coco/camera/__init__.py
annotation_utils/coco/camera/camera.py
annotation_utils/coco/dataset_specific/__init__.py
annotation_utils/coco/dataset_specific/measure_dataset.py
annotation_utils/coco/eval/__init__.py
annotation_utils/coco/eval/ap.py
annotation_utils/coco/eval/bbox.py
annotation_utils/coco/eval/keypoint.py
annotation_utils/coco/eval/result.py
annotation_utils/coco/structs/__init__.py
annotation_utils/coco/structs/dataset.py
annotation_utils/coco/structs/handlers.py
annotation_utils/coco/structs/misc.py
annotation_utils/coco/structs/objects.py
annotation_utils/coco/structs/zoom.py
annotation_utils/coco/util/__init__.py
annotation_utils/coco/util/id_map.py
annotation_utils/coco/util/image_iter.py
annotation_utils/coco/wrappers/__init__.py
annotation_utils/coco/wrappers/infer_wrappers.py
annotation_utils/dataset/__init__.py
annotation_utils/dataset/dataset_prep.py
annotation_utils/dataset/config/__init__.py
annotation_utils/dataset/config/dataset_config.py
annotation_utils/dataset/config/path.py
annotation_utils/detectron/__init__.py
annotation_utils/detectron/structs/__init__.py
annotation_utils/detectron/structs/dataset.py
annotation_utils/labelme/__init__.py
annotation_utils/labelme/structs/__init__.py
annotation_utils/labelme/structs/ann.py
annotation_utils/linemod/__init__.py
annotation_utils/linemod/objects.py
annotation_utils/ndds/__init__.py
annotation_utils/ndds/base.py
annotation_utils/ndds/coco_base.py
annotation_utils/ndds/common/__init__.py
annotation_utils/ndds/common/angle.py
annotation_utils/ndds/common/camera.py
annotation_utils/ndds/common/cuboid.py
annotation_utils/ndds/common/cuboid0.py
annotation_utils/ndds/common/point.py
annotation_utils/ndds/structs/__init__.py
annotation_utils/ndds/structs/annotation.py
annotation_utils/ndds/structs/dataset.py
pyclay_annotation_utils-0.3.9.dist-info/LICENSE
pyclay_annotation_utils-0.3.9.dist-info/METADATA
pyclay_annotation_utils-0.3.9.dist-info/WHEEL
pyclay_annotation_utils-0.3.9.dist-info/top_level.txt
pyclay_annotation_utils-0.3.9.dist-info/RECORD
