Metadata-Version: 2.1
Name: pyclay-annotation-utils
Version: 0.3.9
Summary: Utilities that are used for assisting with making annotated data.
Home-page: https://github.com/cm107/annotation_utils
Author: Clayton Mork
Author-email: mork.clayton3@gmail.com
License: MIT License
Platform: UNKNOWN
Classifier: Programming Language :: Python :: 3
Classifier: License :: OSI Approved :: MIT License
Classifier: Operating System :: OS Independent
Requires-Python: >=3.7
Requires-Dist: opencv-python (>=4.1.1.26)
Requires-Dist: numpy (>=1.17.2)
Requires-Dist: Shapely (>=1.6.4.post2)
Requires-Dist: matplotlib
Requires-Dist: plotly
Requires-Dist: Pillow (>=6.1.0)
Requires-Dist: pycocotools (>=2.0.0)
Requires-Dist: pylint (>=2.4.2)
Requires-Dist: labelme (>=3.16.7)
Requires-Dist: PyYAML (>=5.1.2)
Requires-Dist: pyqt5 (>=5.14.1)
Requires-Dist: pandas (>=1.0.4)
Requires-Dist: xlrd (>=1.2.0)
Requires-Dist: pyclay-streamer (>=0.1.4)
